video2chars-0.7.0.dist-info/METADATA
video2chars-0.7.0.dist-info/WHEEL
video2chars-0.7.0.dist-info/entry_points.txt
video2chars-0.7.0.dist-info/licenses/LICENSE
video2chars/DroidSansMono.ttf
video2chars/__init__.py
video2chars/__main__.py
video2chars/converter.py
video2chars-0.7.0.dist-info/RECORD
