Metadata-Version: 2.1
Name: video2chars
Version: 0.7.0
Summary: Convert video to character art animation.
Author-Email: Ryan Yin <ryan4yin@linux.com>
License: MIT
Classifier: Programming Language :: Python :: 3
Classifier: License :: OSI Approved :: MIT License
Classifier: Operating System :: OS Independent
Project-URL: Homepage, https://github.com/yuansuye/video2chars
Project-URL: Issues, https://github.com/yuansuye/video2chars/issues
Requires-Python: >=3.9
Requires-Dist: numpy<1.27.0,>=1.25.0
Requires-Dist: pillow<10.0.0,>=9.5.0
Requires-Dist: click<9.0.0,>=8.0.0
Requires-Dist: moviepy<1.1.0,>=1.0.3
Requires-Dist: imageio-ffmpeg<0.5.0,>=0.4.9
